tbmp
